mads/__init__.py
mads/mads.py
mads-0.0.4.dist-info/METADATA
mads-0.0.4.dist-info/WHEEL
mads-0.0.4.dist-info/licenses/LICENSE
mads-0.0.4.dist-info/RECORD
