Metadata-Version: 2.1
Name: mads
Version: 0.0.4
Summary: An implementation of Mesh Adaptive Direct Search (MADS) for gradient-free optimization.
Project-URL: Homepage, https://gitlab.com/bvermeir/mads
Project-URL: Bug Tracker, https://gitlab.com/bvermeir/mads/-/issues
Author-email: "Brian C. Vermeire" <brian.vermeire@concordia.ca>
License-File: LICENSE
Classifier: License :: OSI Approved :: MIT License
Classifier: Operating System :: OS Independent
Classifier: Programming Language :: Python :: 3
Requires-Python: >=3.7
